dynaccount/__init__.py
dynaccount/client.py
dynaccount/export.py
dynaccount/logging_config.py
dynaccount/util.py
dynaccount-0.1.0.dist-info/METADATA
dynaccount-0.1.0.dist-info/WHEEL
dynaccount-0.1.0.dist-info/licenses/LICENSE
dynaccount-0.1.0.dist-info/RECORD
