Metadata-Version: 2.4
Name: dynaccount
Version: 0.1.0
Summary: An easier way to programmatically leverage Account Management in Dynatrace. Please review the README. Project URLs are currently broken but will work once project is uploaded to public GitHub repo.
Project-URL: Homepage, https://github.com/wallisga/dynaccount
Project-URL: Issues, https://github.com/wallisga/dynaccount/issues
Author-email: Gavin Wallis <gwallis.msu@gmail.com>
License-Expression: MIT
License-File: LICENSE
Classifier: Operating System :: OS Independent
Classifier: Programming Language :: Python :: 3
Requires-Python: >=3.8
Requires-Dist: requests
